chatmcp_memory/__init__.py
chatmcp_memory/__main__.py
chatmcp_memory/dto.py
chatmcp_memory/remember.py
chatmcp_memory-0.0.8.dist-info/METADATA
chatmcp_memory-0.0.8.dist-info/WHEEL
chatmcp_memory-0.0.8.dist-info/entry_points.txt
chatmcp_memory-0.0.8.dist-info/licenses/LICENSE
chatmcp_memory-0.0.8.dist-info/RECORD
