Metadata-Version: 2.4
Name: chatmcp_memory
Version: 0.0.8
Summary: An MCP server able to give large language models the power to remember.
Project-URL: Homepage, https://github.com/vearne/chatmcp_memory
Author-email: vearne <asdwoshiaotian@gmail.com>
License: MIT
License-File: LICENSE
Requires-Python: >=3.8
Requires-Dist: fastmcp==2.10.5
Requires-Dist: pydantic==2.11.7
